intrascan/__init__.py
intrascan/cli.py
intrascan/executor.py
intrascan/extractors.py
intrascan/frida_client.py
intrascan/matchers.py
intrascan/models.py
intrascan/output.py
intrascan/request_builder.py
intrascan/template_discovery.py
intrascan/template_parser.py
intrascan/variables.py
intrascan/platforms/__init__.py
intrascan-0.1.1.dist-info/licenses/LICENSE
intrascan-0.1.1.dist-info/METADATA
intrascan-0.1.1.dist-info/WHEEL
intrascan-0.1.1.dist-info/entry_points.txt
intrascan-0.1.1.dist-info/top_level.txt
intrascan-0.1.1.dist-info/RECORD
