Metadata-Version: 2.4
Name: intrascan
Version: 0.1.1
Summary: iOS/Android security scanner using Nuclei templates via Frida
Author: Xplo8E
License: MIT
Project-URL: Homepage, https://github.com/Xplo8E/intrascan
Project-URL: Repository, https://github.com/Xplo8E/intrascan
Project-URL: Documentation, https://github.com/Xplo8E/intrascan#readme
Project-URL: Issues, https://github.com/Xplo8E/intrascan/issues
Keywords: security,scanner,nuclei,frida,mobile,ios,android,mdm,penetration-testing,vulnerability-scanner
Classifier: Development Status :: 4 - Beta
Classifier: Environment :: Console
Classifier: Intended Audience :: Developers
Classifier: Intended Audience :: Information Technology
Classifier: License :: OSI Approved :: MIT License
Classifier: Operating System :: MacOS
Classifier: Operating System :: POSIX :: Linux
Classifier: Programming Language :: Python :: 3
Classifier: Programming Language :: Python :: 3.10
Classifier: Programming Language :: Python :: 3.11
Classifier: Programming Language :: Python :: 3.12
Classifier: Programming Language :: Python :: 3.13
Classifier: Topic :: Security
Classifier: Topic :: Software Development :: Testing
Requires-Python: >=3.10
License-File: LICENSE
Requires-Dist: frida>=16.7.11
Requires-Dist: frida-tools>=13.7.1
Requires-Dist: PyYAML>=6.0
Requires-Dist: click>=8.0
Provides-Extra: dev
Requires-Dist: pytest>=7.0; extra == "dev"
Requires-Dist: pytest-cov>=4.0; extra == "dev"
Requires-Dist: build; extra == "dev"
Requires-Dist: twine; extra == "dev"
Dynamic: license-file
